cosave/__init__.py
cosave/cli.py
cosave/commands/__init__.py
cosave/commands/add.py
cosave/commands/backup.py
cosave/commands/delete.py
cosave/commands/list.py
cosave/commands/restore.py
cosave/commands/update.py
cosave/utils/__init__.py
cosave/utils/executor.py
cosave/utils/loader.py
cosave/utils/saver.py
cosave/utils/variables.py
cosave-0.9.6.dist-info/METADATA
cosave-0.9.6.dist-info/WHEEL
cosave-0.9.6.dist-info/entry_points.txt
cosave-0.9.6.dist-info/top_level.txt
cosave-0.9.6.dist-info/RECORD
